LICENSE
README.md
setup.py
reconchess_tools/__init__.py
reconchess_tools/mht.py
reconchess_tools/stockfish.py
reconchess_tools/strategy.py
reconchess_tools/utilities.py
reconchess_tools.egg-info/PKG-INFO
reconchess_tools.egg-info/SOURCES.txt
reconchess_tools.egg-info/dependency_links.txt
reconchess_tools.egg-info/entry_points.txt
reconchess_tools.egg-info/requires.txt
reconchess_tools.egg-info/top_level.txt
reconchess_tools/cli/__init__.py
reconchess_tools/cli/main.py
reconchess_tools/example_bot/__init__.py
reconchess_tools/example_bot/bot.py
reconchess_tools/ui/__init__.py
reconchess_tools/ui/replay.py