Metadata-Version: 2.1
Name: reconchess-tools
Version: 0.2.1
Summary: Tools for developing bots to play reconchess.
Home-page: https://github.com/raaperrotta/reconchess-tools
Author: Robert Perrotta
Author-email: raaperrotta@gmail.com
License: MIT
Platform: UNKNOWN
Classifier: License :: OSI Approved :: BSD License
Classifier: Programming Language :: Python
Classifier: Programming Language :: Python :: 3
Classifier: Programming Language :: Python :: 3.6
Classifier: Programming Language :: Python :: 3.7
Classifier: Programming Language :: Python :: 3.8
Classifier: Programming Language :: Python :: 3.9
Classifier: Programming Language :: Python :: Implementation :: CPython
Classifier: Programming Language :: Python :: Implementation :: PyPy
Requires-Python: >=3.6.0
License-File: LICENSE
